[
  {
    "date": "2026-04-15",
    "sku": "Dried-Kadayif-180gm",
    "expectedSalesPpc": 1194.09,
    "notes": "Eligible",
    "productLabel": "B0F9WZ117F-Dried-Kadayif-180gm"
  },
  {
    "date": "2026-04-15",
    "sku": "Pistachio-Cream-1kg-New2",
    "expectedSalesPpc": 660.79,
    "notes": "Eligible",
    "productLabel": "B0G2LC4FHK-Pistachio-Cream-1kg-New2"
  },
  {
    "date": "2026-04-15",
    "sku": "Choco-Milk-200g",
    "expectedSalesPpc": 271.63,
    "notes": "Eligible",
    "productLabel": "B0FZ5T3DK4-Choco-Milk-200g"
  },
  {
    "date": "2026-04-15",
    "sku": "Choco-Blueberry-100g",
    "expectedSalesPpc": 222.05,
    "notes": "Eligible",
    "productLabel": "B0FZ65RH16-Choco-Blueberry-100g"
  },
  {
    "date": "2026-04-15",
    "sku": "Pistachio-Cream-200g-New2",
    "expectedSalesPpc": 163.11,
    "notes": "Eligible",
    "productLabel": "B0G2L7V5L9-Pistachio-Cream-200g-New2"
  },
  {
    "date": "2026-04-15",
    "sku": "Choco-Dark-200g",
    "expectedSalesPpc": 141.39,
    "notes": "Eligible",
    "productLabel": "B0FZ6C1BN2-Choco-Dark-200g"
  },
  {
    "date": "2026-04-15",
    "sku": "Choco-White-100g",
    "expectedSalesPpc": 137.29,
    "notes": "Eligible",
    "productLabel": "B0FZ5XNZTT-Choco-White-100g"
  },
  {
    "date": "2026-04-15",
    "sku": "Dried-Kadayif-400gm",
    "expectedSalesPpc": 92.92,
    "notes": "Eligible",
    "productLabel": "B0F7LZFZTT-Dried-Kadayif-400gm"
  },
  {
    "date": "2026-04-15",
    "sku": "Choco-Brownie-100g",
    "expectedSalesPpc": 87.8,
    "notes": "Eligible",
    "productLabel": "B0FZ5PPSP3-Choco-Brownie-100g"
  },
  {
    "date": "2026-04-15",
    "sku": "Choco-White-200g",
    "expectedSalesPpc": 84.51,
    "notes": "Eligible",
    "productLabel": "B0G1FGJ81B-Choco-White-200g"
  },
  {
    "date": "2026-04-15",
    "sku": "Pistachio-Butter-200g-New2",
    "expectedSalesPpc": 79.96,
    "notes": "Eligible",
    "productLabel": "B0G2KZGRNH-Pistachio-Butter-200g-New2"
  },
  {
    "date": "2026-04-15",
    "sku": "Roasted-Kataifi-180g",
    "expectedSalesPpc": 78.95,
    "notes": "Eligible",
    "productLabel": "B0GDMPMB2X-Roasted-Kataifi-180g"
  },
  {
    "date": "2026-04-15",
    "sku": "Dried-Kadayif-10KG",
    "expectedSalesPpc": 64.99,
    "notes": "Eligible",
    "productLabel": "B0F7LX896Y-Dried-Kadayif-10KG"
  },
  {
    "date": "2026-04-15",
    "sku": "Roasted-Kataifi-400g",
    "expectedSalesPpc": 57.47,
    "notes": "Eligible",
    "productLabel": "B0GDMFCD5N-Roasted-Kataifi-400g"
  },
  {
    "date": "2026-04-15",
    "sku": "Choco-Pumpkin-100g",
    "expectedSalesPpc": 51.92,
    "notes": "Eligible",
    "productLabel": "B0FZ61M15L-Choco-Pumpkin-100g"
  },
  {
    "date": "2026-04-15",
    "sku": "Choco-Milk-100g",
    "expectedSalesPpc": 27.86,
    "notes": "Eligible",
    "productLabel": "B0FZ5VPR5Q-Choco-Milk-100g"
  },
  {
    "date": "2026-04-15",
    "sku": "Roasted-Kadayif-10KG",
    "expectedSalesPpc": 12.99,
    "notes": "Eligible",
    "productLabel": "B0F9RSWGFZ-Roasted-Kadayif-10KG"
  },
  {
    "date": "2026-04-15",
    "sku": "ORG Dell 9-Cell D620",
    "expectedSalesPpc": 0,
    "notes": "No data available",
    "productLabel": "1094441252-ORG Dell 9-Cell D620"
  },
  {
    "date": "2026-04-15",
    "sku": "N_DYSON_MattressTool",
    "expectedSalesPpc": 0,
    "notes": "No data available",
    "productLabel": "B000ANKHBE-N_DYSON_MattressTool"
  },
  {
    "date": "2026-04-15",
    "sku": "N_Dyson_Multi-Angle Brush",
    "expectedSalesPpc": 0,
    "notes": "No data available",
    "productLabel": "B000V53CO0-N_Dyson_Multi-Angle Brush"
  },
  {
    "date": "2026-04-15",
    "sku": "TC Electronic ND-1 Nova",
    "expectedSalesPpc": 0,
    "notes": "No data available",
    "productLabel": "B000X1WD56-TC Electronic ND-1 Nova"
  },
  {
    "date": "2026-04-15",
    "sku": "PR01X w/PA-10 Adapter",
    "expectedSalesPpc": 0,
    "notes": "No data available",
    "productLabel": "B0011WHFPE-PR01X w/PA-10 Adapter"
  },
  {
    "date": "2026-04-15",
    "sku": "9 cell 9400 Battery",
    "expectedSalesPpc": 0,
    "notes": "No data available",
    "productLabel": "B001JDI2FM-9 cell 9400 Battery"
  },
  {
    "date": "2026-04-15",
    "sku": "Rep Dell D500/600 2200 MAH",
    "expectedSalesPpc": 0,
    "notes": "No data available",
    "productLabel": "B001MRX31I-Rep Dell D500/600 2200 MAH"
  },
  {
    "date": "2026-04-15",
    "sku": "Adapter PA-6 C600",
    "expectedSalesPpc": 0,
    "notes": "No data available",
    "productLabel": "B0026K2MRQ-Adapter PA-6 C600"
  }
]
